Metadata-Version: 2.1
Name: readtagger
Version: 0.5.25
Summary: Tags reads in a BAM file based on other BAM files.
Home-page: https://github.com/bardin-lab/readtagger
Author: Marius van den Beek
Author-email: m.vandenbeek@gmail.com
License: MIT
Keywords: Bioinformatics
Platform: UNKNOWN
Classifier: Development Status :: 5 - Production/Stable
Classifier: Intended Audience :: Developers
Classifier: Environment :: Console
Classifier: Operating System :: POSIX
Classifier: Topic :: Scientific/Engineering :: Bio-Informatics
Classifier: Natural Language :: English
Classifier: Programming Language :: Python :: 3
Requires-Dist: bcbio-gff
Requires-Dist: biopython
Requires-Dist: cached-property
Requires-Dist: click
Requires-Dist: contextlib2
Requires-Dist: compare-reads
Requires-Dist: edlib
Requires-Dist: matplotlib
Requires-Dist: mappy
Requires-Dist: multiprocessing-logging
Requires-Dist: pandas
Requires-Dist: pysam
Requires-Dist: scipy
Requires-Dist: six
Provides-Extra: testing
Requires-Dist: pytest ; extra == 'testing'
Requires-Dist: pytest-datadir ; extra == 'testing'
Requires-Dist: tox ; extra == 'testing'
Requires-Dist: planemo ; extra == 'testing'
Requires-Dist: cookiecutter ; extra == 'testing'
Requires-Dist: bumpversion ; extra == 'testing'
